README.rst
setup.cfg
setup.py
simple_wbd/__init__.py
simple_wbd/climate.py
simple_wbd/filters.py
simple_wbd/indicators.py
simple_wbd/utils.py
simple_wbd.egg-info/PKG-INFO
simple_wbd.egg-info/SOURCES.txt
simple_wbd.egg-info/dependency_links.txt
simple_wbd.egg-info/requires.txt
simple_wbd.egg-info/top_level.txt