Metadata-Version: 1.1
Name: simple-wbd
Version: 0.2.1
Summary: A simple python interface for World Bank Data Indicator and Climate APIs
Home-page: https://github.com/zidarsk8/simple_wbd
Author: Miha Zidar
Author-email: zidarsk8@gmail.com
License: MIT
Download-URL: https://github.com/zidarsk8/simple_wbd/tarball/0.2.1
Keywords: World Bank Data,indicator api,climate api
Platform: UNKNOWN
Classifier: Development Status :: 3 - Alpha
Classifier: Environment :: Console
Classifier: Intended Audience :: Developers
Classifier: Intended Audience :: Science/Research
Classifier: License :: OSI Approved :: MIT License
Classifier: Operating System :: OS Independent
Classifier: Programming Language :: Python :: 3
Classifier: Topic :: Scientific/Engineering
Provides: simple_wbd
